jsonreme/__init__.py
jsonreme/consts.py
jsonreme/drift.py
jsonreme/exception.py
jsonreme/remediator.py
jsonreme-1.0.3.dist-info/METADATA
jsonreme-1.0.3.dist-info/WHEEL
jsonreme-1.0.3.dist-info/top_level.txt
jsonreme-1.0.3.dist-info/RECORD
